arcane/pinterest/__init__.py
arcane/pinterest/const.py
arcane/pinterest/exceptions.py
arcane/pinterest/lib.py
arcane/pinterest/pinterest.py
arcane/pinterest/types.py
arcane_pinterest-2.3.0.dist-info/METADATA
arcane_pinterest-2.3.0.dist-info/WHEEL
arcane_pinterest-2.3.0.dist-info/RECORD
